pisegment/__init__.py
pisegment/annotator.py
pisegment/cli.py
pisegment/segmentation.py
pisegment-0.3.dist-info/LICENSE
pisegment-0.3.dist-info/METADATA
pisegment-0.3.dist-info/WHEEL
pisegment-0.3.dist-info/entry_points.txt
pisegment-0.3.dist-info/top_level.txt
pisegment-0.3.dist-info/RECORD
